TOPSIS_NAMAN_BANSAL_101803202/__init__.py
TOPSIS_NAMAN_BANSAL_101803202/topsis.py
TOPSIS_NAMAN_BANSAL_101803202-1.0.0.dist-info/LICENSE
TOPSIS_NAMAN_BANSAL_101803202-1.0.0.dist-info/METADATA
TOPSIS_NAMAN_BANSAL_101803202-1.0.0.dist-info/WHEEL
TOPSIS_NAMAN_BANSAL_101803202-1.0.0.dist-info/entry_points.txt
TOPSIS_NAMAN_BANSAL_101803202-1.0.0.dist-info/top_level.txt
TOPSIS_NAMAN_BANSAL_101803202-1.0.0.dist-info/RECORD
