Metadata-Version: 2.1
Name: TOPSIS-NAMAN-BANSAL-101803202
Version: 1.0.0
Summary: A Python package OF TOPSIS.
Home-page: UNKNOWN
Author: Naman_Bansal
Author-email: naman.bansal101@gmail.com
License: MIT
Platform: UNKNOWN
Classifier: License :: OSI Approved :: MIT License
Classifier: Programming Language :: Python :: 3
Classifier: Programming Language :: Python :: 3.7
Requires-Dist: requests
